{"cameraMode":{"drawMode":0,"name":"Shaded","section":"Shading Mode"},"sceneLighting":true,"audioPlay":false,"sceneViewState":{"showFog":true,"showMaterialUpdate":false,"showSkybox":true,"showFlares":true,"showImageEffects":true,"showParticleSystems":true},"in2DMode":false,"pivot":{"x":1.257383108139038,"y":-1.2622523307800294,"z":1.6485228538513184},"rotation":{"x":0.22799207270145417,"y":-0.5736075043678284,"z":0.17453432083129884,"w":0.7680320739746094},"size":2.2203831672668459,"orthographic":false}